{
    "git.autofetch": true,
    "editor.quickSuggestions": {
        "other": true,
        "comments": true,
        "strings": true
    },
    "editor.quickSuggestionsDelay": 100,
    "editor.autoClosingBrackets": "always",
    "editor.formatOnSave": true,
    "editor.minimap.enabled": false,
    "files.autoSave": "afterDelay",
    "explorer.confirmDelete": false,
    "explorer.confirmDragAndDrop": false,
    "window.zoomLevel": -1,
    "python.pythonPath": "/usr/local/bin/python3",
    "python.formatting.provider": "black",
    "python.linting.enabled": true,
    "python.linting.pylintEnabled": true,
    "code-runner.executorMap": {
        "python": "$pythonPath -u $fullFileName"
    },
    "code-runner.clearPreviousOutput": true,
    "code-runner.showExecutionMessage": false,
    "code-runner.ignoreSelection": true,
    "code-runner.saveFileBeforeRun": true,
    "workbench.startupEditor": "none",
    "workbench.editor.closeOnFileDelete": true,
    "workbench.settings.openDefaultKeybindings": true,
    "workbench.settings.useSplitJSON": true,
    "workbench.settings.openDefaultSettings": true,
    "workbench.settings.editor": "json",
    "workbench.statusBar.visible": false,
    "workbench.colorTheme": "GitHub Light Default",
    "workbench.iconTheme": "ayu",
    "workbench.editorAssociations": [
        {
            "viewType": "jupyter.notebook.ipynb",
            "filenamePattern": "*.ipynb"
        }
    ],
    "path-intellisense.showHiddenFiles": true,
    "path-intellisense.autoSlashAfterDirectory": true,
    "path-intellisense.absolutePathToWorkspace": true,
    "path-intellisense.extensionOnImport": true,
    "typescript.suggest.paths": false,
    "markdown-preview-enhanced.automaticallyShowPreviewOfMarkdownBeingEdited": false,
    "markdown-preview-enhanced.enableCriticMarkupSyntax": true,
    "markdown-preview-enhanced.enableExtendedTableSyntax": true,
    "markdown-preview-enhanced.enableHTML5Embed": true,
    "markdown-preview-enhanced.enableScriptExecution": true,
    "markdown-preview-enhanced.enableTypographer": true,
    "markdown-preview-enhanced.printBackground": true,
    "markdown-preview-enhanced.Bucket": "",
    "markdown-links.autoStart": true
}